kernelpipes/__init__.py
kernelpipes/pipeline.py
kernelpipes/steps/__init__.py
kernelpipes/steps/check.py
kernelpipes/steps/kernel.py
kernelpipes/steps/output.py
kernelpipes/steps/status.py
kernelpipes/steps/step.py
kernelpipes-1.2.1.dist-info/LICENSE
kernelpipes-1.2.1.dist-info/METADATA
kernelpipes-1.2.1.dist-info/WHEEL
kernelpipes-1.2.1.dist-info/entry_points.txt
kernelpipes-1.2.1.dist-info/top_level.txt
kernelpipes-1.2.1.dist-info/RECORD
