Metadata-Version: 2.1
Name: kernelpipes
Version: 1.2.1
Summary: Kaggle Kernel Pipelines
Home-page: https://github.com/neuml/kernelpipes
Author: NeuML
License: Apache 2.0: http://www.apache.org/licenses/LICENSE-2.0
Project-URL: Documentation, https://github.com/neuml/kernelpipes
Project-URL: Issue Tracker, https://github.com/neuml/kernelpipes/issues
Project-URL: Source Code, https://github.com/neuml/kernelpipes
Keywords: kaggle job task machine-learning
Platform: UNKNOWN
Classifier: License :: OSI Approved :: Apache Software License
Classifier: Operating System :: OS Independent
Classifier: Programming Language :: Python :: 3
Classifier: Topic :: Software Development
Classifier: Topic :: Utilities
Requires-Python: >=3.6
Requires-Dist: croniter (>=0.3.32)
Requires-Dist: kaggle (>=1.5.6)
Requires-Dist: PyYAML (>=5.3)
